Metadata-Version: 1.2
Name: xinceptio
Version: 0.0.3
Summary: DSM Oracle
Home-page: UNKNOWN
Author: Zong Xin
Author-email: xin.zong@inceptio.ai
License: Apache License 2.0
Platform: UNKNOWN
Classifier: Development Status :: 5 - Production/Stable
Classifier: License :: OSI Approved :: Apache Software License
Classifier: Operating System :: OS Independent
Classifier: Programming Language :: Python
Classifier: Topic :: Utilities
Classifier: Topic :: Software Development
Classifier: Topic :: Security
Requires-Python: >=3.6
